sllib/__init__.py
sllib/definitions.py
sllib/frame.py
sllib/header.py
sllib/reader.py
sllib-0.2.3.dist-info/LICENSE
sllib-0.2.3.dist-info/METADATA
sllib-0.2.3.dist-info/WHEEL
sllib-0.2.3.dist-info/top_level.txt
sllib-0.2.3.dist-info/RECORD
