Metadata-Version: 2.1
Name: sllib
Version: 0.2.3
Summary: Library for reading SLG, SL2 and SL3 files from Lowrance fishfinders
Home-page: https://github.com/opensounder/python-sllib
Author: Peter Magnusson
Author-email: me@kmpm.se
License: UNKNOWN
Project-URL: Bug Tracker, https://github.com/opensounder/python-sllib/issues
Platform: UNKNOWN
Classifier: Programming Language :: Python :: 3
Classifier: License :: OSI Approved :: MIT License
Classifier: Operating System :: OS Independent
Requires-Python: >=3.6
License-File: LICENSE
